{"SiteObjectives": {"Site": [
  {
    "@SiteLink": "http://www.londonair.org.uk/london/asp/publicstats.asp?site=IS2",
    "@SiteCode": "IS2",
    "@DataOwner": "Islington",
    "@Longitude": "-0.116146",
    "@Latitude": "51.555378",
    "@SiteName": "Islington - Holloway Road",
    "@DataManager": "King's College London",
    "@SiteType": "Roadside",
    "@LatitudeWGS84": "6720127.92666",
    "@LongitudeWGS84": "-12929.3135777",
    "Objective": [
      {
        "@SpeciesDescription": "PM10 (not reference equiv.)",
        "@Year": "2016",
        "@ObjectiveName": "40 ug/m3 as an annual mean",
        "@SpeciesCode": "DUST",
        "@Achieved": "YES",
        "@Value": "22"
      },
      {
        "@SpeciesDescription": "PM10 (not reference equiv.)",
        "@Year": "2016",
        "@ObjectiveName": "50 ug/m3 as a 24 hour mean, not to be exceeded more than 35 times a year",
        "@SpeciesCode": "DUST",
        "@Achieved": "YES",
        "@Value": "1"
      },
      {
        "@SpeciesDescription": "Nitrogen Dioxide",
        "@Year": "2016",
        "@ObjectiveName": "200 ug/m3 as a 1 hour mean, not to be exceeded more than 18 times a year",
        "@SpeciesCode": "NO2",
        "@Achieved": "YES",
        "@Value": "0"
      },
      {
        "@SpeciesDescription": "Nitrogen Dioxide",
        "@Year": "2016",
        "@ObjectiveName": "40 ug/m3 as an annual mean",
        "@SpeciesCode": "NO2",
        "@Achieved": "NO",
        "@Value": "60"
      },
      {
        "@SpeciesDescription": "PM10 Particulate",
        "@Year": "2016",
        "@ObjectiveName": "40 ug/m3 as an annual mean",
        "@SpeciesCode": "PM10",
        "@Achieved": "YES",
        "@Value": "22"
      },
      {
        "@SpeciesDescription": "PM10 Particulate",
        "@Year": "2016",
        "@ObjectiveName": "50 ug/m3 as a 24 hour mean, not to be exceeded more than 35 times a year",
        "@SpeciesCode": "PM10",
        "@Achieved": "YES",
        "@Value": "3"
      }
    ]
  },
  {
    "@SiteLink": "http://www.londonair.org.uk/london/asp/publicstats.asp?site=IS6",
    "@SiteCode": "IS6",
    "@DataOwner": "Islington",
    "@Longitude": "-0.106989",
    "@Latitude": "51.557895",
    "@SiteName": "Islington - Arsenal",
    "@DataManager": "King's College London",
    "@SiteType": "Urban Background",
    "@LatitudeWGS84": "6720578.5826",
    "@LongitudeWGS84": "-11909.9610005",
    "Objective": [
      {
        "@SpeciesDescription": "PM10 (not reference equiv.)",
        "@Year": "2016",
        "@ObjectiveName": "40 ug/m3 as an annual mean",
        "@SpeciesCode": "DUST",
        "@Achieved": "YES",
        "@Value": "17"
      },
      {
        "@SpeciesDescription": "PM10 (not reference equiv.)",
        "@Year": "2016",
        "@ObjectiveName": "50 ug/m3 as a 24 hour mean, not to be exceeded more than 35 times a year",
        "@SpeciesCode": "DUST",
        "@Achieved": "YES",
        "@Value": "0"
      },
      {
        "@SpeciesDescription": "Nitrogen Dioxide",
        "@Year": "2016",
        "@ObjectiveName": "200 ug/m3 as a 1 hour mean, not to be exceeded more than 18 times a year",
        "@SpeciesCode": "NO2",
        "@Achieved": "YES",
        "@Value": "0"
      },
      {
        "@SpeciesDescription": "Nitrogen Dioxide",
        "@Year": "2016",
        "@ObjectiveName": "40 ug/m3 as an annual mean",
        "@SpeciesCode": "NO2",
        "@Achieved": "YES",
        "@Value": "35"
      },
      {
        "@SpeciesDescription": "PM10 Particulate",
        "@Year": "2016",
        "@ObjectiveName": "40 ug/m3 as an annual mean",
        "@SpeciesCode": "PM10",
        "@Achieved": "YES",
        "@Value": "17"
      },
      {
        "@SpeciesDescription": "PM10 Particulate",
        "@Year": "2016",
        "@ObjectiveName": "50 ug/m3 as a 24 hour mean, not to be exceeded more than 35 times a year",
        "@SpeciesCode": "PM10",
        "@Achieved": "YES",
        "@Value": "2"
      }
    ]
  }
]}}