{"SiteObjectives": {"Site": [
  {
    "@SiteLink": "http://www.londonair.org.uk/london/asp/publicstats.asp?site=KC1",
    "@SiteCode": "KC1",
    "@DataOwner": "Department for Environment Food and Rural Affairs",
    "@Longitude": "-0.213492139585065",
    "@Latitude": "51.5210467476039",
    "@SiteName": "Kensington and Chelsea - North Ken",
    "@DataManager": "King's College London",
    "@SiteType": "Urban Background",
    "@LatitudeWGS84": "6713983.58013",
    "@LongitudeWGS84": "-23765.836267",
    "Objective": [
      {
        "@SpeciesDescription": "Carbon Monoxide",
        "@Year": "2016",
        "@ObjectiveName": "10 mg/m3 as a maximum daily running 8 hour mean",
        "@SpeciesCode": "CO",
        "@Achieved": "YES",
        "@Value": "0"
      },
      {
        "@SpeciesDescription": "PM10 (not reference equiv.)",
        "@Year": "2016",
        "@ObjectiveName": "40 ug/m3 as an annual mean",
        "@SpeciesCode": "DUST",
        "@Achieved": "YES",
        "@Value": "17"
      },
      {
        "@SpeciesDescription": "PM10 (not reference equiv.)",
        "@Year": "2016",
        "@ObjectiveName": "50 ug/m3 as a 24 hour mean, not to be exceeded more than 35 times a year",
        "@SpeciesCode": "DUST",
        "@Achieved": "YES",
        "@Value": "2"
      },
      {
        "@SpeciesDescription": "Nitrogen Dioxide",
        "@Year": "2016",
        "@ObjectiveName": "200 ug/m3 as a 1 hour mean, not to be exceeded more than 18 times a year",
        "@SpeciesCode": "NO2",
        "@Achieved": "YES",
        "@Value": "0"
      },
      {
        "@SpeciesDescription": "Nitrogen Dioxide",
        "@Year": "2016",
        "@ObjectiveName": "40 ug/m3 as an annual mean",
        "@SpeciesCode": "NO2",
        "@Achieved": "YES",
        "@Value": "34"
      },
      {
        "@SpeciesDescription": "Ozone",
        "@Year": "2016",
        "@ObjectiveName": "100 ug/m3 as an 8 hour mean, not to be exceeded more than 10 times a year",
        "@SpeciesCode": "O3",
        "@Achieved": "YES",
        "@Value": "0"
      },
      {
        "@SpeciesDescription": "PM10 Particulate",
        "@Year": "2016",
        "@ObjectiveName": "40 ug/m3 as an annual mean",
        "@SpeciesCode": "PM10",
        "@Achieved": "YES",
        "@Value": "17"
      },
      {
        "@SpeciesDescription": "PM10 Particulate",
        "@Year": "2016",
        "@ObjectiveName": "50 ug/m3 as a 24 hour mean, not to be exceeded more than 35 times a year",
        "@SpeciesCode": "PM10",
        "@Achieved": "YES",
        "@Value": "2"
      },
      {
        "@SpeciesDescription": "Sulphur Dioxide",
        "@Year": "2016",
        "@ObjectiveName": "125 ug/m3 as a 24 hour mean, not to be exceeded more than 3 times a year",
        "@SpeciesCode": "SO2",
        "@Achieved": "YES",
        "@Value": "0"
      },
      {
        "@SpeciesDescription": "Sulphur Dioxide",
        "@Year": "2016",
        "@ObjectiveName": "266 ug/m3 as a 15 minute mean, not to be exceeded more than 35 times a year",
        "@SpeciesCode": "SO2",
        "@Achieved": "YES",
        "@Value": "0"
      },
      {
        "@SpeciesDescription": "Sulphur Dioxide",
        "@Year": "2016",
        "@ObjectiveName": "350 ug/m3 as a 1 hour mean, not to be exceeded more than 24 times a year",
        "@SpeciesCode": "SO2",
        "@Achieved": "YES",
        "@Value": "0"
      }
    ]
  },
  {
    "@SiteLink": "http://www.londonair.org.uk/london/asp/publicstats.asp?site=KC2",
    "@SiteCode": "KC2",
    "@DataOwner": "Department for Environment Food and Rural Affairs",
    "@Longitude": "-0.178809464",
    "@Latitude": "51.49550391",
    "@SiteName": "Kensington and Chelsea - Cromwell Road",
    "@DataManager": "King's College London",
    "@SiteType": "Roadside",
    "@LatitudeWGS84": "6709415.12178",
    "@LongitudeWGS84": "-19904.9784815",
    "Objective": [
      {
        "@SpeciesDescription": "Nitrogen Dioxide",
        "@Year": "2016",
        "@ObjectiveName": "200 ug/m3 as a 1 hour mean, not to be exceeded more than 18 times a year",
        "@SpeciesCode": "NO2",
        "@Achieved": "YES",
        "@Value": "1"
      },
      {
        "@SpeciesDescription": "Nitrogen Dioxide",
        "@Year": "2016",
        "@ObjectiveName": "40 ug/m3 as an annual mean",
        "@SpeciesCode": "NO2",
        "@Achieved": "NO",
        "@Value": "68"
      },
      {
        "@SpeciesDescription": "PM10 Particulate",
        "@Year": "2016",
        "@ObjectiveName": "40 ug/m3 as an annual mean",
        "@SpeciesCode": "PM10",
        "@Achieved": "YES",
        "@Value": "23"
      },
      {
        "@SpeciesDescription": "PM10 Particulate",
        "@Year": "2016",
        "@ObjectiveName": "50 ug/m3 as a 24 hour mean, not to be exceeded more than 35 times a year",
        "@SpeciesCode": "PM10",
        "@Achieved": "YES",
        "@Value": "4"
      }
    ]
  },
  {
    "@SiteLink": "http://www.londonair.org.uk/london/asp/publicstats.asp?site=KC3",
    "@SiteCode": "KC3",
    "@DataOwner": "Kensington and Chelsea",
    "@Longitude": "-0.164337605",
    "@Latitude": "51.49913951",
    "@SiteName": "Kensington and Chelsea - Knightsbridge",
    "@DataManager": "King's College London",
    "@SiteType": "Roadside",
    "@LatitudeWGS84": "6710065.20988",
    "@LongitudeWGS84": "-18293.9785068",
    "Objective": [
      {
        "@SpeciesDescription": "Nitrogen Dioxide",
        "@Year": "2016",
        "@ObjectiveName": "200 ug/m3 as a 1 hour mean, not to be exceeded more than 18 times a year",
        "@SpeciesCode": "NO2",
        "@Achieved": "NO",
        "@Value": "82"
      },
      {
        "@SpeciesDescription": "Nitrogen Dioxide",
        "@Year": "2016",
        "@ObjectiveName": "40 ug/m3 as an annual mean",
        "@SpeciesCode": "NO2",
        "@Achieved": "NO",
        "@Value": "80"
      }
    ]
  },
  {
    "@SiteLink": "http://www.londonair.org.uk/london/asp/publicstats.asp?site=KC4",
    "@SiteCode": "KC4",
    "@DataOwner": "Kensington and Chelsea",
    "@Longitude": "-0.168397129",
    "@Latitude": "51.48743685",
    "@SiteName": "Kensington and Chelsea - Kings Road",
    "@DataManager": "King's College London",
    "@SiteType": "Roadside",
    "@LatitudeWGS84": "6707972.82158",
    "@LongitudeWGS84": "-18745.8826513",
    "Objective": [
      {
        "@SpeciesDescription": "Nitrogen Dioxide",
        "@Year": "2016",
        "@ObjectiveName": "200 ug/m3 as a 1 hour mean, not to be exceeded more than 18 times a year",
        "@SpeciesCode": "NO2",
        "@Achieved": "YES",
        "@Value": "1"
      },
      {
        "@SpeciesDescription": "Nitrogen Dioxide",
        "@Year": "2016",
        "@ObjectiveName": "40 ug/m3 as an annual mean",
        "@SpeciesCode": "NO2",
        "@Achieved": "NO",
        "@Value": "74"
      }
    ]
  },
  {
    "@SiteLink": "http://www.londonair.org.uk/london/asp/publicstats.asp?site=KC5",
    "@SiteCode": "KC5",
    "@DataOwner": "Kensington and Chelsea",
    "@Longitude": "-0.190863311",
    "@Latitude": "51.49019756",
    "@SiteName": "Kensington and Chelsea - Earls Court Rd",
    "@DataManager": "King's College London",
    "@SiteType": "Kerbside",
    "@LatitudeWGS84": "6708466.37696",
    "@LongitudeWGS84": "-21246.8065916",
    "Objective": [
      {
        "@SpeciesDescription": "Nitrogen Dioxide",
        "@Year": "2016",
        "@ObjectiveName": "200 ug/m3 as a 1 hour mean, not to be exceeded more than 18 times a year",
        "@SpeciesCode": "NO2",
        "@Achieved": "NO",
        "@Value": "44"
      },
      {
        "@SpeciesDescription": "Nitrogen Dioxide",
        "@Year": "2016",
        "@ObjectiveName": "40 ug/m3 as an annual mean",
        "@SpeciesCode": "NO2",
        "@Achieved": "NO",
        "@Value": "86"
      },
      {
        "@SpeciesDescription": "PM10 Particulate",
        "@Year": "2016",
        "@ObjectiveName": "40 ug/m3 as an annual mean",
        "@SpeciesCode": "PM10",
        "@Achieved": "YES",
        "@Value": "22"
      },
      {
        "@SpeciesDescription": "PM10 Particulate",
        "@Year": "2016",
        "@ObjectiveName": "50 ug/m3 as a 24 hour mean, not to be exceeded more than 35 times a year",
        "@SpeciesCode": "PM10",
        "@Achieved": "YES",
        "@Value": "0"
      }
    ]
  },
  {
    "@SiteLink": "http://www.londonair.org.uk/london/asp/publicstats.asp?site=KC7",
    "@SiteCode": "KC7",
    "@DataOwner": "Kensington and Chelsea",
    "@Longitude": "-0.21344617",
    "@Latitude": "51.52106551",
    "@SiteName": "Kensington and Chelsea - North Ken FDMS",
    "@DataManager": "King's College London",
    "@SiteType": "Urban Background",
    "@LatitudeWGS84": "6713986.93682",
    "@LongitudeWGS84": "-23760.7189562",
    "Objective": [
      {
        "@SpeciesDescription": "PM10 Particulate",
        "@Year": "2016",
        "@ObjectiveName": "40 ug/m3 as an annual mean",
        "@SpeciesCode": "PM10",
        "@Achieved": "YES",
        "@Value": "20"
      },
      {
        "@SpeciesDescription": "PM10 Particulate",
        "@Year": "2016",
        "@ObjectiveName": "50 ug/m3 as a 24 hour mean, not to be exceeded more than 35 times a year",
        "@SpeciesCode": "PM10",
        "@Achieved": "YES",
        "@Value": "4"
      }
    ]
  }
]}}